{
    "js": [
        "js/dataTables.semanticui.js",
        "js/dataTables.semanticui.min.js",
        "js/dataTables.semanticui.min.mjs",
        "js/dataTables.semanticui.mjs"
    ],
    "css": [
        "css/dataTables.semanticui.css",
        "css/dataTables.semanticui.min.css"
    ],
    "types": [
        "types/dataTables.semanticui.d.ts"
    ],
    "src-repo": "http://github.com/DataTables/DataTablesSrc",
    "last-tag": "2.0.5",
    "last-sync": "5d287f0379e0d950e49961658b16734943c357f8"
}